flightcondition/__init__.py
flightcondition/__main__.py
flightcondition/atmosphere.py
flightcondition/boundarylayer.py
flightcondition/common.py
flightcondition/constants.py
flightcondition/flightcondition.py
flightcondition/isentropicflow.py
flightcondition/nondimensional.py
flightcondition/normalshock.py
flightcondition/units.py
flightcondition/data/constants_en.txt
flightcondition/data/fc_units_en.txt
flightcondition-24.6.22.dist-info/LICENSE
flightcondition-24.6.22.dist-info/METADATA
flightcondition-24.6.22.dist-info/WHEEL
flightcondition-24.6.22.dist-info/entry_points.txt
flightcondition-24.6.22.dist-info/top_level.txt
flightcondition-24.6.22.dist-info/zip-safe
flightcondition-24.6.22.dist-info/RECORD
