Metadata-Version: 2.1
Name: flightcondition
Version: 24.6.22
Summary: Airspeed conversions (true/calibrated/equivalent/Mach),
Home-page: https://github.com/MattCJones/flightcondition
Author: Matthew C. Jones
Author-email: matt.c.jones.aoe@gmail.com
License: MIT License
Keywords: utility,aerospace,engineering,design
Classifier: Development Status :: 4 - Beta
Classifier: Intended Audience :: Science/Research
Classifier: License :: OSI Approved :: MIT License
Classifier: Natural Language :: English
Classifier: Operating System :: OS Independent
Classifier: Topic :: Scientific/Engineering
Classifier: Topic :: Utilities
Classifier: Programming Language :: Python :: 3.8
Classifier: Programming Language :: Python :: 3.9
Requires-Python: >=3.8
License-File: LICENSE
Requires-Dist: numpy
Requires-Dist: pint
Requires-Dist: pymsis
Requires-Dist: setuptools
Provides-Extra: test
Requires-Dist: pytest ; extra == 'test'
